{
    "$schema": "http://json-schema.org/draft-04/schema#",
    "$ref": "#/definitions/TpmsSensors",
    "definitions": {
        "PbConfigs.TpmsSensorIds": {
            "required": [
                "fl",
                "fr",
                "rl",
                "rr"
            ],
            "properties": {
                "fl": {
                    "type": "integer"
                },
                "fr": {
                    "type": "integer"
                },
                "rl": {
                    "type": "integer"
                },
                "rr": {
                    "type": "integer"
                }
            },
            "additionalProperties": false,
            "type": "object",
            "title": "Tpms Sensor Ids"
        },
        "TpmsSensors": {
            "required": [
                "enabled",
                "rtl433Path",
                "recordSignals",
                "sensorIds"
            ],
            "properties": {
                "enabled": {
                    "type": "boolean"
                },
                "rtl433Path": {
                    "type": "string"
                },
                "recordSignals": {
                    "type": "boolean"
                },
                "sensorIds": {
                    "$ref": "#/definitions/PbConfigs.TpmsSensorIds",
                    "additionalProperties": false
                }
            },
            "additionalProperties": false,
            "type": "object",
            "title": "Tpms Sensors"
        }
    }
}